{"cookies": [{"name": "ig_did", "value": "3FB3A55F-3443-4C82-B0F2-A8CE7FC24BBC", "domain": ".threads.net", "path": "/", "expires": 1774082238.310727, "httpOnly": true, "secure": true, "sameSite": "None"}, {"name": "dpr", "value": "1", "domain": ".threads.net", "path": "/", "expires": 1743151046, "httpOnly": false, "secure": true, "sameSite": "None"}, {"name": "csrftoken", "value": "ZQEpgr6XgHMS4BskjSxj3GRZfV6NqEAL", "domain": ".threads.net", "path": "/", "expires": 1773995850.212576, "httpOnly": false, "secure": true, "sameSite": "Lax"}, {"name": "mid", "value": "Z90lQAAEAAET_b6aFF9xhztzih4C", "domain": ".threads.net", "path": "/", "expires": 1777106245.803588, "httpOnly": false, "secure": true, "sameSite": "Lax"}, {"name": "ds_user_id", "value": "73473762243", "domain": ".threads.net", "path": "/", "expires": 1750322250.213443, "httpOnly": false, "secure": true, "sameSite": "Lax"}, {"name": "sessionid", "value": "73473762243%3Afd5G7SxEOyaZm1%3A6%3AAYdrG0M2z9L-PnC8fM_NTmogx01MEi3G0ai7ZgrQtA", "domain": ".threads.net", "path": "/", "expires": 1774082245.803757, "httpOnly": true, "secure": true, "sameSite": "None"}, {"name": "rur", "value": "\"NHA\\05473473762243\\0541774082250:01f77c3fd784314e0bb764a3af8e83bfb12693e57e5d6b5d65fca77f73380be5fdde051e\"", "domain": ".threads.net", "path": "/", "expires": -1, "httpOnly": true, "secure": true, "sameSite": "Lax"}], "origins": [{"origin": "https://www.threads.net", "localStorage": [{"name": "signal_flush_timestamp", "value": "1742546238537"}, {"name": "Session", "value": "bsixzx:1742546285032"}, {"name": "hb_timestamp", "value": "1742546238527"}, {"name": "banzai:last_storage_flush", "value": "1742546239441.4001"}]}]}